magic_docker.py
magic_docker-0.0.13.dist-info/METADATA
magic_docker-0.0.13.dist-info/WHEEL
magic_docker-0.0.13.dist-info/license
magic_docker-0.0.13.dist-info/top_level.txt
magic_docker-0.0.13.dist-info/RECORD
