Metadata-Version: 2.1
Name: magic-docker
Version: 0.0.13
Summary: Automated Docker-Image-Builder Extention for Docker
Home-page: https://github.com/BabakEA/magic_docker
Author: Babak EA
Author-email: emami.babak@gmail.com
License: UNKNOWN
Platform: UNKNOWN
License-File: license
Requires-Dist: stdlib-list (>=0.5.0)
Requires-Dist: ipywidgets (==7.5.1)
Requires-Dist: numpy (>=1.18.0)
Provides-Extra: test
Requires-Dist: IPython (>=7.12.0) ; extra == 'test'
Requires-Dist: notebook (>=6.0.1) ; extra == 'test'
